{"updated":"2026-05-15T16:04:19.590103+00:00","count":149,"errors":["^VXMT"],"tickers":{"^VIX":{"symbol":"^VIX","name":"CBOE Volatility Index","price":18.42,"change":1.16,"changePercent":6.7207,"volume":0,"avgVolume":0,"score":3.0,"signal":"BUY","rsi":48.0,"macd":-0.8573,"macdSig":-1.1016,"macdHist":0.2443,"macdUp":false,"macdDn":false,"sma20":18.05,"sma50":21.67,"ema50":19.69,"ema200":19.03,"goldenCross":false,"deathCross":false,"adx":13.2,"diP":29.3,"diN":19.8,"volVs65":null,"c1W":7.16,"c1M":2.68},"^VXMT":{"symbol":"^VXMT","name":"^VXMT","price":null,"change":null,"changePercent":null,"volume":null,"avgVolume":null,"score":null,"signal":"LOADING"},"VIXY":{"symbol":"VIXY","name":"VIX Short-Term Futures ETF","price":27.12,"change":0.4416,"changePercent":1.6552,"volume":2405154,"avgVolume":4611468,"score":-1.0,"signal":"HOLD","rsi":42.9,"macd":-0.8448,"macdSig":-0.9276,"macdHist":0.0828,"macdUp":false,"macdDn":false,"sma20":27.64,"sma50":30.47,"ema50":28.91,"ema200":32.66,"goldenCross":false,"deathCross":false,"adx":9.5,"diP":20.6,"diN":18.1,"volVs65":0.52,"c1W":0.26,"c1M":-4.13},"SPY":{"symbol":"SPY","name":"State Street SPDR S&P 500 ETF T","price":740.55,"change":-7.62,"changePercent":-1.0185,"volume":20706186,"avgVolume":74324525,"score":4.5,"signal":"BUY","rsi":69.5,"macd":15.0819,"macdSig":14.4093,"macdHist":0.6727,"macdUp":false,"macdDn":false,"sma20":723.87,"sma50":689.7,"ema50":703.23,"ema200":671.15,"goldenCross":false,"deathCross":false,"adx":27.8,"diP":37.6,"diN":21.3,"volVs65":0.28,"c1W":0.4,"c1M":5.54},"QQQ":{"symbol":"QQQ","name":"Invesco QQQ Trust, Series 1","price":710.78,"change":-9.0099,"changePercent":-1.2517,"volume":23442300,"avgVolume":57267133,"score":2.0,"signal":"HOLD","rsi":72.8,"macd":24.6453,"macdSig":22.8939,"macdHist":1.7513,"macdUp":false,"macdDn":false,"sma20":680.45,"sma50":631.33,"ema50":649.6,"ema200":608.41,"goldenCross":false,"deathCross":false,"adx":39.8,"diP":40.6,"diN":19.7,"volVs65":0.41,"c1W":-0.06,"c1M":10.98},"^DJI":{"symbol":"^DJI","name":"Dow Jones Industrial Average","price":49571.08,"change":-492.3828,"changePercent":-0.9835,"volume":244907593,"avgVolume":521059039,"score":3.0,"signal":"BUY","rsi":56.2,"macd":443.2066,"macdSig":476.6411,"macdHist":-33.4345,"macdUp":false,"macdDn":false,"sma20":49454.78,"sma50":47989.79,"ema50":48701.53,"ema200":47323.96,"goldenCross":false,"deathCross":false,"adx":21.1,"diP":28.4,"diN":20.3,"volVs65":0.47,"c1W":-0.08,"c1M":2.04},"^HSI":{"symbol":"^HSI","name":"HANG SENG INDEX","price":26389.04,"change":0.5996,"changePercent":0.0023,"volume":3124300000,"avgVolume":3173667692,"score":4.0,"signal":"BUY","rsi":55.5,"macd":161.1277,"macdSig":134.3023,"macdHist":26.8254,"macdUp":false,"macdDn":false,"sma20":26185.7,"sma50":25767.69,"ema50":26029.91,"ema200":25727.28,"goldenCross":false,"deathCross":false,"adx":8.9,"diP":36.0,"diN":26.5,"volVs65":0.98,"c1W":-0.89,"c1M":2.0},"TQQQ":{"symbol":"TQQQ","name":"ProShares UltraPro QQQ","price":75.88,"change":-3.07,"changePercent":-3.8885,"volume":50188524,"avgVolume":96071488,"score":2.0,"signal":"HOLD","rsi":71.4,"macd":6.5984,"macdSig":5.9528,"macdHist":0.6455,"macdUp":false,"macdDn":false,"sma20":67.35,"sma50":55.06,"ema50":59.87,"ema200":51.64,"goldenCross":false,"deathCross":false,"adx":40.1,"diP":40.3,"diN":20.9,"volVs65":0.52,"c1W":-0.52,"c1M":34.47},"GLD":{"symbol":"GLD","name":"SPDR Gold Shares","price":416.6,"change":-10.61,"changePercent":-2.4836,"volume":5266217,"avgVolume":11024987,"score":3.0,"signal":"BUY","rsi":39.8,"macd":-2.3721,"macdSig":-2.4142,"macdHist":0.0421,"macdUp":false,"macdDn":false,"sma20":427.93,"sma50":434.37,"ema50":432.9,"ema200":402.76,"goldenCross":false,"deathCross":false,"adx":19.0,"diP":20.4,"diN":39.5,"volVs65":0.47,"c1W":-3.96,"c1M":-5.34},"SLV":{"symbol":"SLV","name":"iShares Silver Trust","price":69.01,"change":-6.4951,"changePercent":-8.6016,"volume":29213868,"avgVolume":41943184,"score":4.0,"signal":"BUY","rsi":46.4,"macd":1.478,"macdSig":0.9265,"macdHist":0.5516,"macdUp":false,"macdDn":false,"sma20":70.48,"sma50":69.72,"ema50":70.72,"ema200":60.58,"goldenCross":false,"deathCross":false,"adx":16.2,"diP":32.5,"diN":38.4,"volVs65":0.68,"c1W":-5.47,"c1M":-3.12},"PALL":{"symbol":"PALL","name":"abrdn Physical Palladium Shares","price":128.03,"change":-3.0908,"changePercent":-2.3572,"volume":177304,"avgVolume":249773,"score":2.0,"signal":"HOLD","rsi":38.9,"macd":-1.7087,"macdSig":-1.215,"macdHist":-0.4937,"macdUp":false,"macdDn":false,"sma20":135.67,"sma50":137.29,"ema50":139.01,"ema200":133.9,"goldenCross":false,"deathCross":false,"adx":16.3,"diP":22.9,"diN":39.7,"volVs65":0.71,"c1W":-4.96,"c1M":-9.42},"USO":{"symbol":"USO","name":"United States Oil Fund","price":147.75,"change":4.7499,"changePercent":3.3216,"volume":2711705,"avgVolume":33355827,"score":3.0,"signal":"BUY","rsi":61.3,"macd":5.1177,"macdSig":5.3534,"macdHist":-0.2357,"macdUp":false,"macdDn":false,"sma20":138.55,"sma50":128.0,"ema50":125.89,"ema200":95.44,"goldenCross":false,"deathCross":false,"adx":22.2,"diP":38.2,"diN":24.8,"volVs65":0.08,"c1W":10.6,"c1M":17.41},"COPX":{"symbol":"COPX","name":"Global X Copper Miners ETF","price":83.04,"change":-6.345,"changePercent":-7.0989,"volume":3711841,"avgVolume":4479288,"score":4.0,"signal":"BUY","rsi":49.3,"macd":1.7705,"macdSig":1.1871,"macdHist":0.5834,"macdUp":false,"macdDn":false,"sma20":83.2,"sma50":80.37,"ema50":82.28,"ema200":70.93,"goldenCross":false,"deathCross":false,"adx":17.0,"diP":30.1,"diN":31.3,"volVs65":0.82,"c1W":-3.41,"c1M":-3.68},"EWJ":{"symbol":"EWJ","name":"iShares MSCI Japan Index Fund","price":91.13,"change":-0.93,"changePercent":-1.0102,"volume":2882744,"avgVolume":9325092,"score":4.0,"signal":"BUY","rsi":56.7,"macd":1.337,"macdSig":1.1415,"macdHist":0.1955,"macdUp":false,"macdDn":false,"sma20":89.55,"sma50":87.15,"ema50":88.39,"ema200":82.97,"goldenCross":false,"deathCross":false,"adx":12.4,"diP":32.1,"diN":30.8,"volVs65":0.3,"c1W":-1.18,"c1M":1.92},"EWY":{"symbol":"EWY","name":"iShares MSCI South Korea ETF","price":179.55,"change":-10.97,"changePercent":-5.7579,"volume":7580214,"avgVolume":22771875,"score":4.5,"signal":"BUY","rsi":59.4,"macd":12.1564,"macdSig":11.2833,"macdHist":0.8731,"macdUp":false,"macdDn":false,"sma20":168.08,"sma50":146.34,"ema50":152.87,"ema200":115.82,"goldenCross":false,"deathCross":false,"adx":30.1,"diP":33.9,"diN":28.7,"volVs65":0.33,"c1W":-5.6,"c1M":21.75},"IEFA":{"symbol":"IEFA","name":"iShares Core MSCI EAFE ETF","price":95.21,"change":-1.705,"changePercent":-1.7594,"volume":3441190,"avgVolume":14574566,"score":2.5,"signal":"HOLD","rsi":49.2,"macd":0.7079,"macdSig":0.7762,"macdHist":-0.0684,"macdUp":false,"macdDn":true,"sma20":95.69,"sma50":93.45,"ema50":94.58,"ema200":90.11,"goldenCross":false,"deathCross":false,"adx":12.4,"diP":26.8,"diN":38.8,"volVs65":0.23,"c1W":-2.15,"c1M":-1.01},"XLE":{"symbol":"XLE","name":"State Street Energy Select Sect","price":58.97,"change":0.9,"changePercent":1.5499,"volume":17036574,"avgVolume":53709159,"score":4.5,"signal":"BUY","rsi":57.2,"macd":0.1184,"macdSig":0.032,"macdHist":0.0864,"macdUp":true,"macdDn":false,"sma20":57.51,"sma50":57.99,"ema50":56.93,"ema200":50.68,"goldenCross":false,"deathCross":false,"adx":14.2,"diP":31.2,"diN":24.9,"volVs65":0.31,"c1W":5.87,"c1M":4.22},"XLI":{"symbol":"XLI","name":"State Street Industrial Select ","price":171.5,"change":-3.01,"changePercent":-1.7248,"volume":3471992,"avgVolume":11979242,"score":3.0,"signal":"BUY","rsi":48.7,"macd":1.0929,"macdSig":1.3445,"macdHist":-0.2516,"macdUp":false,"macdDn":false,"sma20":173.02,"sma50":169.05,"ema50":170.55,"ema200":161.37,"goldenCross":false,"deathCross":false,"adx":11.3,"diP":18.9,"diN":19.5,"volVs65":0.29,"c1W":-0.98,"c1M":0.69},"XLB":{"symbol":"XLB","name":"State Street Materials Select S","price":50.37,"change":-1.305,"changePercent":-2.5256,"volume":4164494,"avgVolume":14189781,"score":3.0,"signal":"BUY","rsi":41.9,"macd":0.1392,"macdSig":0.2585,"macdHist":-0.1193,"macdUp":false,"macdDn":false,"sma20":51.63,"sma50":50.58,"ema50":50.97,"ema200":47.92,"goldenCross":false,"deathCross":false,"adx":11.1,"diP":20.1,"diN":32.1,"volVs65":0.29,"c1W":-2.37,"c1M":-2.68},"XLK":{"symbol":"XLK","name":"State Street Technology Select ","price":177.12,"change":-2.38,"changePercent":-1.3259,"volume":7772148,"avgVolume":15097436,"score":2.0,"signal":"HOLD","rsi":74.5,"macd":8.295,"macdSig":7.4892,"macdHist":0.8058,"macdUp":false,"macdDn":false,"sma20":165.59,"sma50":149.72,"ema50":155.5,"ema200":142.62,"goldenCross":false,"deathCross":false,"adx":37.3,"diP":40.8,"diN":19.8,"volVs65":0.51,"c1W":0.91,"c1M":16.51},"XLF":{"symbol":"XLF","name":"State Street Financial Select S","price":51.13,"change":-0.16,"changePercent":-0.312,"volume":11670713,"avgVolume":48662237,"score":-1.0,"signal":"HOLD","rsi":47.1,"macd":0.046,"macdSig":0.1806,"macdHist":-0.1346,"macdUp":false,"macdDn":false,"sma20":51.7,"sma50":50.6,"ema50":51.3,"ema200":51.75,"goldenCross":false,"deathCross":false,"adx":11.9,"diP":21.3,"diN":19.8,"volVs65":0.24,"c1W":-0.21,"c1M":-1.73},"XLV":{"symbol":"XLV","name":"State Street Health Care Select","price":145.44,"change":-1.19,"changePercent":-0.8116,"volume":4359648,"avgVolume":12470434,"score":3.0,"signal":"BUY","rsi":48.3,"macd":-0.4746,"macdSig":-0.7876,"macdHist":0.3129,"macdUp":false,"macdDn":false,"sma20":145.14,"sma50":146.75,"ema50":147.26,"ema200":145.95,"goldenCross":false,"deathCross":false,"adx":12.9,"diP":20.4,"diN":22.3,"volVs65":0.35,"c1W":1.36,"c1M":-0.8},"XLY":{"symbol":"XLY","name":"State Street Consumer Discretio","price":116.62,"change":-2.05,"changePercent":-1.7275,"volume":3442262,"avgVolume":10041854,"score":4.5,"signal":"BUY","rsi":47.3,"macd":0.9563,"macdSig":1.3148,"macdHist":-0.3585,"macdUp":false,"macdDn":false,"sma20":118.51,"sma50":114.37,"ema50":116.44,"ema200":115.42,"goldenCross":true,"deathCross":false,"adx":18.3,"diP":22.9,"diN":27.7,"volVs65":0.34,"c1W":-2.98,"c1M":-0.86},"XLP":{"symbol":"XLP","name":"State Street Consumer Staples S","price":84.68,"change":-0.3,"changePercent":-0.353,"volume":4721800,"avgVolume":16493884,"score":4.0,"signal":"BUY","rsi":57.8,"macd":0.5067,"macdSig":0.3617,"macdHist":0.1451,"macdUp":false,"macdDn":false,"sma20":83.6,"sma50":82.96,"ema50":83.36,"ema200":81.43,"goldenCross":false,"deathCross":false,"adx":14.7,"diP":23.8,"diN":18.6,"volVs65":0.28,"c1W":0.59,"c1M":3.99},"XLC":{"symbol":"XLC","name":"State Street Communication Serv","price":116.34,"change":-0.77,"changePercent":-0.6575,"volume":1693038,"avgVolume":6588954,"score":3.0,"signal":"BUY","rsi":51.5,"macd":0.3981,"macdSig":0.4972,"macdHist":-0.099,"macdUp":false,"macdDn":false,"sma20":116.59,"sma50":114.84,"ema50":115.64,"ema200":113.22,"goldenCross":false,"deathCross":false,"adx":10.3,"diP":29.5,"diN":29.3,"volVs65":0.25,"c1W":-0.51,"c1M":-2.1},"XLU":{"symbol":"XLU","name":"State Street Utilities Select S","price":44.15,"change":-0.755,"changePercent":-1.6815,"volume":7601085,"avgVolume":25163907,"score":2.0,"signal":"HOLD","rsi":36.2,"macd":-0.3626,"macdSig":-0.1821,"macdHist":-0.1805,"macdUp":false,"macdDn":false,"sma20":45.58,"sma50":45.9,"ema50":45.57,"ema200":43.95,"goldenCross":false,"deathCross":false,"adx":17.9,"diP":14.0,"diN":31.3,"volVs65":0.3,"c1W":-1.29,"c1M":-4.76},"XLRE":{"symbol":"XLRE","name":"State Street Real Estate Select","price":43.31,"change":-0.605,"changePercent":-1.3778,"volume":2575600,"avgVolume":7771421,"score":3.0,"signal":"BUY","rsi":45.1,"macd":0.3212,"macdSig":0.4713,"macdHist":-0.1501,"macdUp":false,"macdDn":false,"sma20":44.09,"sma50":42.78,"ema50":43.18,"ema200":41.74,"goldenCross":false,"deathCross":false,"adx":18.7,"diP":19.2,"diN":26.8,"volVs65":0.32,"c1W":-2.49,"c1M":-1.15},"CVX":{"symbol":"CVX","name":"Chevron Corporation","price":188.94,"change":2.3,"changePercent":1.2323,"volume":3138052,"avgVolume":11880919,"score":3.5,"signal":"BUY","rsi":50.8,"macd":-1.3878,"macdSig":-1.6086,"macdHist":0.2208,"macdUp":true,"macdDn":false,"sma20":187.21,"sma50":193.0,"ema50":188.07,"ema200":170.58,"goldenCross":false,"deathCross":false,"adx":17.6,"diP":24.9,"diN":26.6,"volVs65":0.26,"c1W":4.03,"c1M":0.42},"XOM":{"symbol":"XOM","name":"Exxon Mobil Corporation","price":156.13,"change":3.355,"changePercent":2.196,"volume":8689537,"avgVolume":21090865,"score":3.0,"signal":"BUY","rsi":57.1,"macd":-0.4526,"macdSig":-1.1026,"macdHist":0.65,"macdUp":false,"macdDn":false,"sma20":150.73,"sma50":154.93,"ema50":151.36,"ema200":134.48,"goldenCross":false,"deathCross":false,"adx":13.5,"diP":29.1,"diN":23.5,"volVs65":0.41,"c1W":8.0,"c1M":2.73},"COP":{"symbol":"COP","name":"ConocoPhillips","price":121.68,"change":2.705,"changePercent":2.2737,"volume":2474061,"avgVolume":9557742,"score":2.0,"signal":"HOLD","rsi":52.7,"macd":-0.9627,"macdSig":-0.905,"macdHist":-0.0577,"macdUp":false,"macdDn":false,"sma20":120.13,"sma50":122.26,"ema50":118.92,"ema200":105.51,"goldenCross":false,"deathCross":false,"adx":14.0,"diP":29.6,"diN":28.1,"volVs65":0.26,"c1W":7.65,"c1M":0.83},"OXY":{"symbol":"OXY","name":"Occidental Petroleum Corporatio","price":58.82,"change":1.98,"changePercent":3.4835,"volume":7862141,"avgVolume":16797259,"score":3.5,"signal":"BUY","rsi":54.7,"macd":-0.3537,"macdSig":-0.3854,"macdHist":0.0318,"macdUp":true,"macdDn":false,"sma20":57.18,"sma50":58.45,"ema50":56.41,"ema200":49.58,"goldenCross":false,"deathCross":false,"adx":16.3,"diP":31.1,"diN":26.3,"volVs65":0.47,"c1W":10.92,"c1M":3.43},"PBR":{"symbol":"PBR","name":"Petroleo Brasileiro S.A. Petrob","price":19.77,"change":-0.01,"changePercent":-0.0506,"volume":5061559,"avgVolume":27758071,"score":2.0,"signal":"HOLD","rsi":42.0,"macd":-0.0767,"macdSig":0.2024,"macdHist":-0.2791,"macdUp":false,"macdDn":false,"sma20":20.92,"sma50":20.27,"ema50":19.78,"ema200":15.87,"goldenCross":false,"deathCross":false,"adx":19.6,"diP":22.0,"diN":32.3,"volVs65":0.18,"c1W":-2.75,"c1M":-7.51},"SLB":{"symbol":"SLB","name":"SLB Limited","price":55.4,"change":-0.35,"changePercent":-0.6278,"volume":3286482,"avgVolume":16661358,"score":3.5,"signal":"BUY","rsi":56.5,"macd":0.8907,"macdSig":1.06,"macdHist":-0.1694,"macdUp":false,"macdDn":false,"sma20":55.04,"sma50":51.76,"ema50":52.5,"ema200":44.74,"goldenCross":false,"deathCross":false,"adx":26.1,"diP":22.1,"diN":14.6,"volVs65":0.19,"c1W":4.0,"c1M":7.09},"CEG":{"symbol":"CEG","name":"Constellation Energy Corporatio","price":268.22,"change":-7.04,"changePercent":-2.5576,"volume":1385534,"avgVolume":3211398,"score":-2.0,"signal":"HOLD","rsi":35.5,"macd":-4.017,"macdSig":0.8768,"macdHist":-4.8939,"macdUp":false,"macdDn":false,"sma20":299.41,"sma50":297.44,"ema50":298.77,"ema200":311.91,"goldenCross":false,"deathCross":false,"adx":18.8,"diP":13.9,"diN":31.5,"volVs65":0.43,"c1W":-11.66,"c1M":-10.34},"GEV":{"symbol":"GEV","name":"GE Vernova Inc.","price":1050.0,"change":-40.53,"changePercent":-3.7165,"volume":1108032,"avgVolume":2433352,"score":3.0,"signal":"BUY","rsi":51.8,"macd":26.6126,"macdSig":36.6461,"macdHist":-10.0335,"macdUp":false,"macdDn":false,"sma20":1077.42,"sma50":966.43,"ema50":981.55,"ema200":768.94,"goldenCross":false,"deathCross":false,"adx":20.5,"diP":19.2,"diN":15.1,"volVs65":0.45,"c1W":0.95,"c1M":7.33},"ENPH":{"symbol":"ENPH","name":"Enphase Energy, Inc.","price":50.87,"change":2.8553,"changePercent":5.9473,"volume":8027043,"avgVolume":6223952,"score":-1.5,"signal":"HOLD","rsi":78.1,"macd":2.3308,"macdSig":0.4395,"macdHist":1.8912,"macdUp":false,"macdDn":false,"sma20":36.73,"sma50":37.63,"ema50":37.76,"ema200":38.46,"goldenCross":false,"deathCross":false,"adx":21.8,"diP":42.1,"diN":11.9,"volVs65":1.29,"c1W":39.55,"c1M":59.15},"CAT":{"symbol":"CAT","name":"Caterpillar, Inc.","price":884.66,"change":-35.56,"changePercent":-3.8643,"volume":1235803,"avgVolume":2570063,"score":3.0,"signal":"BUY","rsi":57.2,"macd":37.3828,"macdSig":39.3741,"macdHist":-1.9914,"macdUp":false,"macdDn":true,"sma20":867.79,"sma50":781.24,"ema50":805.9,"ema200":643.37,"goldenCross":false,"deathCross":false,"adx":34.6,"diP":28.9,"diN":16.2,"volVs65":0.47,"c1W":-1.43,"c1M":14.71},"UNP":{"symbol":"UNP","name":"Union Pacific Corporation","price":269.46,"change":0.12,"changePercent":0.0446,"volume":1121348,"avgVolume":2984468,"score":3.5,"signal":"BUY","rsi":62.7,"macd":4.0191,"macdSig":4.2312,"macdHist":-0.212,"macdUp":false,"macdDn":false,"sma20":264.38,"sma50":252.73,"ema50":256.59,"ema200":240.93,"goldenCross":false,"deathCross":false,"adx":25.8,"diP":25.5,"diN":15.2,"volVs65":0.37,"c1W":1.82,"c1M":7.32},"GE":{"symbol":"GE","name":"GE Aerospace","price":283.24,"change":-8.3,"changePercent":-2.847,"volume":1922541,"avgVolume":5857779,"score":3.0,"signal":"BUY","rsi":42.9,"macd":-1.439,"macdSig":-1.5768,"macdHist":0.1378,"macdUp":false,"macdDn":false,"sma20":290.39,"sma50":296.53,"ema50":297.8,"ema200":292.92,"goldenCross":false,"deathCross":false,"adx":21.4,"diP":16.5,"diN":27.9,"volVs65":0.33,"c1W":-4.68,"c1M":-5.05},"RTX":{"symbol":"RTX","name":"RTX Corporation","price":172.9,"change":-2.78,"changePercent":-1.5824,"volume":1451810,"avgVolume":5733904,"score":2.5,"signal":"HOLD","rsi":34.0,"macd":-4.4214,"macdSig":-5.0277,"macdHist":0.6063,"macdUp":false,"macdDn":false,"sma20":177.45,"sma50":190.77,"ema50":186.35,"ema200":178.89,"goldenCross":false,"deathCross":false,"adx":37.4,"diP":12.4,"diN":26.9,"volVs65":0.25,"c1W":-1.81,"c1M":-11.72},"LMT":{"symbol":"LMT","name":"Lockheed Martin Corporation","price":516.86,"change":-3.545,"changePercent":-0.6812,"volume":457787,"avgVolume":1547882,"score":2.5,"signal":"HOLD","rsi":34.5,"macd":-20.3713,"macdSig":-24.2228,"macdHist":3.8515,"macdUp":false,"macdDn":false,"sma20":523.44,"sma50":586.08,"ema50":563.46,"ema200":539.3,"goldenCross":false,"deathCross":false,"adx":46.4,"diP":13.7,"diN":29.3,"volVs65":0.29,"c1W":2.04,"c1M":-14.92},"BA":{"symbol":"BA","name":"Boeing Company (The)","price":222.44,"change":-6.77,"changePercent":-2.9536,"volume":4197948,"avgVolume":6724951,"score":4.0,"signal":"BUY","rsi":46.0,"macd":3.3701,"macdSig":4.077,"macdHist":-0.7068,"macdUp":false,"macdDn":true,"sma20":229.8,"sma50":217.96,"ema50":224.25,"ema200":219.5,"goldenCross":true,"deathCross":false,"adx":14.4,"diP":22.4,"diN":28.0,"volVs65":0.62,"c1W":-6.29,"c1M":1.63},"HON":{"symbol":"HON","name":"Honeywell International Inc.","price":212.16,"change":-5.56,"changePercent":-2.5537,"volume":1651264,"avgVolume":3784480,"score":3.0,"signal":"BUY","rsi":40.6,"macd":-2.6958,"macdSig":-3.3685,"macdHist":0.6726,"macdUp":false,"macdDn":false,"sma20":215.59,"sma50":224.45,"ema50":221.55,"ema200":215.35,"goldenCross":false,"deathCross":false,"adx":22.0,"diP":17.6,"diN":25.5,"volVs65":0.43,"c1W":-0.45,"c1M":-7.51},"MMM":{"symbol":"MMM","name":"3M Company","price":145.76,"change":0.635,"changePercent":0.4376,"volume":1782049,"avgVolume":3837349,"score":-1.0,"signal":"HOLD","rsi":49.2,"macd":-1.0453,"macdSig":-1.3953,"macdHist":0.35,"macdUp":false,"macdDn":false,"sma20":145.18,"sma50":147.07,"ema50":148.59,"ema200":153.87,"goldenCross":false,"deathCross":false,"adx":13.0,"diP":21.5,"diN":19.2,"volVs65":0.46,"c1W":1.72,"c1M":-3.18},"DE":{"symbol":"DE","name":"Deere & Company","price":556.61,"change":-18.03,"changePercent":-3.1376,"volume":286408,"avgVolume":1393841,"score":1.5,"signal":"HOLD","rsi":40.9,"macd":-2.3201,"macdSig":-0.9807,"macdHist":-1.3394,"macdUp":false,"macdDn":true,"sma20":578.31,"sma50":579.98,"ema50":577.28,"ema200":538.47,"goldenCross":false,"deathCross":false,"adx":12.8,"diP":20.1,"diN":25.7,"volVs65":0.2,"c1W":-3.17,"c1M":-4.72},"VRT":{"symbol":"VRT","name":"Vertiv Holdings, LLC","price":368.44,"change":-7.79,"changePercent":-2.0705,"volume":2168881,"avgVolume":7460055,"score":4.5,"signal":"BUY","rsi":67.5,"macd":22.2131,"macdSig":19.9827,"macdHist":2.2304,"macdUp":false,"macdDn":false,"sma20":336.41,"sma50":296.59,"ema50":302.83,"ema200":220.43,"goldenCross":false,"deathCross":false,"adx":27.8,"diP":30.5,"diN":15.2,"volVs65":0.28,"c1W":8.37,"c1M":25.26},"UBER":{"symbol":"UBER","name":"Uber Technologies, Inc.","price":74.59,"change":-0.1,"changePercent":-0.1339,"volume":6273517,"avgVolume":17382901,"score":-1.0,"signal":"HOLD","rsi":48.7,"macd":0.2586,"macdSig":0.4072,"macdHist":-0.1486,"macdUp":false,"macdDn":false,"sma20":75.45,"sma50":74.21,"ema50":75.16,"ema200":81.4,"goldenCross":false,"deathCross":false,"adx":10.4,"diP":21.4,"diN":21.9,"volVs65":0.35,"c1W":-1.14,"c1M":-2.47},"AAL":{"symbol":"AAL","name":"American Airlines Group, Inc.","price":12.44,"change":-0.2599,"changePercent":-2.0465,"volume":13814325,"avgVolume":64875085,"score":0.0,"signal":"HOLD","rsi":53.4,"macd":0.2984,"macdSig":0.2767,"macdHist":0.0217,"macdUp":false,"macdDn":false,"sma20":12.23,"sma50":11.52,"ema50":12.18,"ema200":12.63,"goldenCross":false,"deathCross":false,"adx":18.7,"diP":32.9,"diN":25.1,"volVs65":0.21,"c1W":-6.82,"c1M":1.39},"RKLB":{"symbol":"RKLB","name":"Rocket Lab Corporation","price":123.81,"change":-8.74,"changePercent":-6.5937,"volume":11526049,"avgVolume":22959285,"score":4.5,"signal":"BUY","rsi":70.0,"macd":12.7585,"macdSig":8.1175,"macdHist":4.641,"macdUp":false,"macdDn":false,"sma20":93.64,"sma50":79.23,"ema50":85.14,"ema200":66.4,"goldenCross":false,"deathCross":false,"adx":31.8,"diP":41.1,"diN":7.8,"volVs65":0.5,"c1W":17.39,"c1M":49.29},"LUNR":{"symbol":"LUNR","name":"Intuitive Machines, Inc.","price":34.06,"change":-2.465,"changePercent":-6.7497,"volume":7184381,"avgVolume":13086721,"score":4.5,"signal":"BUY","rsi":65.1,"macd":2.8987,"macdSig":2.073,"macdHist":0.8256,"macdUp":false,"macdDn":false,"sma20":28.26,"sma50":23.6,"ema50":24.92,"ema200":17.89,"goldenCross":false,"deathCross":false,"adx":30.8,"diP":31.2,"diN":9.8,"volVs65":0.55,"c1W":17.55,"c1M":24.84},"ASTS":{"symbol":"ASTS","name":"AST SpaceMobile, Inc.","price":79.28,"change":-3.73,"changePercent":-4.4934,"volume":9352196,"avgVolume":15691418,"score":3.0,"signal":"BUY","rsi":50.7,"macd":-2.0386,"macdSig":-3.5199,"macdHist":1.4812,"macdUp":false,"macdDn":false,"sma20":75.03,"sma50":83.62,"ema50":81.55,"ema200":74.1,"goldenCross":false,"deathCross":false,"adx":14.0,"diP":25.3,"diN":21.1,"volVs65":0.59,"c1W":5.64,"c1M":-12.82},"ACHR":{"symbol":"ACHR","name":"Archer Aviation Inc.","price":6.09,"change":-0.315,"changePercent":-4.9142,"volume":15654649,"avgVolume":30848231,"score":0.0,"signal":"HOLD","rsi":50.4,"macd":0.138,"macdSig":0.1005,"macdHist":0.0375,"macdUp":false,"macdDn":false,"sma20":6.06,"sma50":5.88,"ema50":6.18,"ema200":7.88,"goldenCross":false,"deathCross":false,"adx":14.4,"diP":19.4,"diN":18.0,"volVs65":0.5,"c1W":-5.94,"c1M":0.25},"LIN":{"symbol":"LIN","name":"Linde plc","price":505.93,"change":-5.72,"changePercent":-1.118,"volume":674952,"avgVolume":2417500,"score":4.0,"signal":"BUY","rsi":53.2,"macd":2.5853,"macdSig":2.1676,"macdHist":0.4177,"macdUp":false,"macdDn":false,"sma20":503.13,"sma50":497.1,"ema50":495.59,"ema200":469.34,"goldenCross":false,"deathCross":false,"adx":10.8,"diP":25.1,"diN":17.9,"volVs65":0.28,"c1W":2.59,"c1M":1.34},"FCX":{"symbol":"FCX","name":"Freeport-McMoRan, Inc.","price":62.39,"change":-3.75,"changePercent":-5.6698,"volume":7045540,"avgVolume":17096083,"score":4.0,"signal":"BUY","rsi":49.9,"macd":0.5311,"macdSig":0.0143,"macdHist":0.5167,"macdUp":false,"macdDn":false,"sma20":62.16,"sma50":61.15,"ema50":61.75,"ema200":53.91,"goldenCross":false,"deathCross":false,"adx":20.5,"diP":29.3,"diN":28.4,"volVs65":0.41,"c1W":1.2,"c1M":-8.63},"MP":{"symbol":"MP","name":"MP Materials Corp.","price":60.92,"change":0.605,"changePercent":1.0031,"volume":2633242,"avgVolume":5758636,"score":3.0,"signal":"BUY","rsi":46.2,"macd":1.2461,"macdSig":2.248,"macdHist":-1.0019,"macdUp":false,"macdDn":false,"sma20":65.36,"sma50":59.28,"ema50":61.43,"ema200":56.97,"goldenCross":false,"deathCross":false,"adx":23.6,"diP":20.1,"diN":17.2,"volVs65":0.46,"c1W":-9.66,"c1M":-2.22},"NEM":{"symbol":"NEM","name":"Newmont Corporation","price":108.66,"change":-7.67,"changePercent":-6.5933,"volume":3343906,"avgVolume":9262500,"score":4.0,"signal":"BUY","rsi":43.8,"macd":0.6872,"macdSig":0.6364,"macdHist":0.0508,"macdUp":false,"macdDn":false,"sma20":113.39,"sma50":111.73,"ema50":113.23,"ema200":98.8,"goldenCross":false,"deathCross":false,"adx":14.1,"diP":26.3,"diN":29.8,"volVs65":0.36,"c1W":-6.74,"c1M":-4.19},"SHW":{"symbol":"SHW","name":"Sherwin-Williams Company (The)","price":301.23,"change":-7.95,"changePercent":-2.5713,"volume":626021,"avgVolume":1746129,"score":-2.0,"signal":"HOLD","rsi":34.6,"macd":-6.1306,"macdSig":-4.2198,"macdHist":-1.9109,"macdUp":false,"macdDn":false,"sma20":321.58,"sma50":322.66,"ema50":325.39,"ema200":337.65,"goldenCross":false,"deathCross":false,"adx":20.6,"diP":17.2,"diN":37.2,"volVs65":0.36,"c1W":-4.92,"c1M":-9.63},"STX":{"symbol":"STX","name":"Seagate Technology Holdings PLC","price":786.42,"change":-18.344,"changePercent":-2.2794,"volume":1111917,"avgVolume":3945631,"score":2.0,"signal":"HOLD","rsi":70.8,"macd":82.4236,"macdSig":80.2804,"macdHist":2.1432,"macdUp":false,"macdDn":false,"sma20":698.43,"sma50":539.26,"ema50":587.62,"ema200":379.12,"goldenCross":false,"deathCross":false,"adx":55.7,"diP":35.6,"diN":13.2,"volVs65":0.28,"c1W":0.48,"c1M":47.88},"WDC":{"symbol":"WDC","name":"Western Digital Corporation","price":477.18,"change":-11.965,"changePercent":-2.4461,"volume":3273291,"avgVolume":8518096,"score":4.5,"signal":"BUY","rsi":64.8,"macd":39.8043,"macdSig":39.6164,"macdHist":0.1879,"macdUp":false,"macdDn":false,"sma20":441.22,"sma50":358.45,"ema50":379.64,"ema200":242.35,"goldenCross":false,"deathCross":false,"adx":39.5,"diP":27.3,"diN":15.4,"volVs65":0.38,"c1W":-0.59,"c1M":31.93},"NVDA":{"symbol":"NVDA","name":"NVIDIA Corporation","price":228.06,"change":-7.6801,"changePercent":-3.2579,"volume":86203324,"avgVolume":169329412,"score":4.5,"signal":"BUY","rsi":67.5,"macd":9.5534,"macdSig":7.5316,"macdHist":2.0218,"macdUp":false,"macdDn":false,"sma20":210.44,"sma50":193.13,"ema50":199.54,"ema200":183.08,"goldenCross":false,"deathCross":false,"adx":31.2,"diP":36.1,"diN":14.5,"volVs65":0.51,"c1W":5.98,"c1M":14.98},"AMD":{"symbol":"AMD","name":"Advanced Micro Devices, Inc.","price":432.66,"change":-17.04,"changePercent":-3.7892,"volume":14250583,"avgVolume":38278812,"score":2.0,"signal":"HOLD","rsi":70.2,"macd":50.9259,"macdSig":46.9208,"macdHist":4.0051,"macdUp":false,"macdDn":false,"sma20":372.14,"sma50":279.38,"ema50":311.69,"ema200":231.18,"goldenCross":false,"deathCross":false,"adx":53.5,"diP":40.6,"diN":15.0,"volVs65":0.37,"c1W":-4.95,"c1M":55.49},"MU":{"symbol":"MU","name":"Micron Technology, Inc.","price":731.72,"change":-44.285,"changePercent":-5.7068,"volume":28131021,"avgVolume":43466815,"score":4.5,"signal":"BUY","rsi":67.4,"macd":88.9997,"macdSig":73.8946,"macdHist":15.1051,"macdUp":false,"macdDn":false,"sma20":606.02,"sma50":486.32,"ema50":527.07,"ema200":347.71,"goldenCross":false,"deathCross":false,"adx":42.3,"diP":41.1,"diN":21.8,"volVs65":0.64,"c1W":-2.02,"c1M":60.03},"INTC":{"symbol":"INTC","name":"Intel Corporation","price":108.93,"change":-7.0,"changePercent":-6.0381,"volume":75315578,"avgVolume":111364748,"score":4.5,"signal":"BUY","rsi":62.4,"macd":15.0084,"macdSig":14.8902,"macdHist":0.1183,"macdUp":false,"macdDn":false,"sma20":97.58,"sma50":69.5,"ema50":78.84,"ema200":50.43,"goldenCross":false,"deathCross":false,"adx":60.0,"diP":36.5,"diN":18.3,"volVs65":0.67,"c1W":-12.8,"c1M":59.02},"QCOM":{"symbol":"QCOM","name":"QUALCOMM Incorporated","price":200.58,"change":0.5,"changePercent":0.2499,"volume":11199399,"avgVolume":16652252,"score":6.0,"signal":"BUY","rsi":62.0,"macd":19.5522,"macdSig":17.5735,"macdHist":1.9787,"macdUp":false,"macdDn":false,"sma20":176.78,"sma50":148.96,"ema50":162.17,"ema200":155.32,"goldenCross":true,"deathCross":false,"adx":44.6,"diP":36.1,"diN":19.1,"volVs65":0.67,"c1W":-8.45,"c1M":49.16},"AVGO":{"symbol":"AVGO","name":"Broadcom Inc.","price":426.42,"change":-13.37,"changePercent":-3.0401,"volume":7457496,"avgVolume":23587030,"score":3.5,"signal":"BUY","rsi":59.2,"macd":16.0649,"macdSig":18.1087,"macdHist":-2.0438,"macdUp":false,"macdDn":false,"sma20":418.6,"sma50":369.28,"ema50":384.24,"ema200":340.64,"goldenCross":false,"deathCross":false,"adx":26.7,"diP":31.1,"diN":19.6,"volVs65":0.31,"c1W":-0.83,"c1M":7.01},"MRVL":{"symbol":"MRVL","name":"Marvell Technology, Inc.","price":178.7,"change":-3.88,"changePercent":-2.1251,"volume":11269762,"avgVolume":23400054,"score":3.5,"signal":"BUY","rsi":67.5,"macd":13.7852,"macdSig":14.3039,"macdHist":-0.5187,"macdUp":false,"macdDn":false,"sma20":164.69,"sma50":128.2,"ema50":136.95,"ema200":100.06,"goldenCross":false,"deathCross":false,"adx":48.2,"diP":36.4,"diN":13.2,"volVs65":0.48,"c1W":5.04,"c1M":33.99},"AMAT":{"symbol":"AMAT","name":"Applied Materials, Inc.","price":437.8,"change":-2.76,"changePercent":-0.6265,"volume":6542617,"avgVolume":6944631,"score":4.0,"signal":"BUY","rsi":62.3,"macd":16.3229,"macdSig":14.1515,"macdHist":2.1714,"macdUp":false,"macdDn":false,"sma20":411.46,"sma50":380.83,"ema50":387.84,"ema200":304.25,"goldenCross":false,"deathCross":false,"adx":18.5,"diP":30.0,"diN":24.9,"volVs65":0.94,"c1W":0.54,"c1M":12.29},"LRCX":{"symbol":"LRCX","name":"Lam Research Corporation","price":285.94,"change":-13.21,"changePercent":-4.4158,"volume":5020814,"avgVolume":9830897,"score":4.0,"signal":"BUY","rsi":57.8,"macd":12.9503,"macdSig":11.8987,"macdHist":1.0516,"macdUp":false,"macdDn":false,"sma20":273.27,"sma50":247.89,"ema50":255.85,"ema200":196.1,"goldenCross":false,"deathCross":false,"adx":19.4,"diP":27.9,"diN":24.4,"volVs65":0.51,"c1W":-2.76,"c1M":9.57},"KLAC":{"symbol":"KLAC","name":"KLA Corporation","price":1833.13,"change":-59.8099,"changePercent":-3.1596,"volume":358831,"avgVolume":959563,"score":3.0,"signal":"BUY","rsi":55.5,"macd":48.5064,"macdSig":52.0557,"macdHist":-3.5493,"macdUp":false,"macdDn":false,"sma20":1814.11,"sma50":1653.73,"ema50":1690.34,"ema200":1370.27,"goldenCross":false,"deathCross":false,"adx":12.6,"diP":27.1,"diN":24.9,"volVs65":0.37,"c1W":-1.93,"c1M":5.67},"ASML":{"symbol":"ASML","name":"ASML Holding N.V. - New York Re","price":1518.01,"change":-66.4957,"changePercent":-4.1966,"volume":1004857,"avgVolume":1681723,"score":4.0,"signal":"BUY","rsi":53.9,"macd":40.3738,"macdSig":33.0072,"macdHist":7.3666,"macdUp":false,"macdDn":false,"sma20":1478.46,"sma50":1415.53,"ema50":1436.49,"ema200":1208.89,"goldenCross":false,"deathCross":false,"adx":14.1,"diP":27.8,"diN":26.9,"volVs65":0.6,"c1W":-4.65,"c1M":7.83},"TXN":{"symbol":"TXN","name":"Texas Instruments Incorporated","price":305.5,"change":-2.67,"changePercent":-0.8664,"volume":2231983,"avgVolume":7045310,"score":2.0,"signal":"HOLD","rsi":77.5,"macd":21.6278,"macdSig":20.6253,"macdHist":1.0025,"macdUp":false,"macdDn":false,"sma20":277.55,"sma50":230.4,"ema50":246.24,"ema200":207.03,"goldenCross":false,"deathCross":false,"adx":57.6,"diP":42.7,"diN":10.0,"volVs65":0.31,"c1W":6.15,"c1M":37.63},"ADI":{"symbol":"ADI","name":"Analog Devices, Inc.","price":419.28,"change":-7.51,"changePercent":-1.7596,"volume":1179282,"avgVolume":3740904,"score":4.5,"signal":"BUY","rsi":64.4,"macd":19.3124,"macdSig":19.2232,"macdHist":0.0892,"macdUp":false,"macdDn":false,"sma20":403.48,"sma50":356.42,"ema50":370.62,"ema200":305.96,"goldenCross":false,"deathCross":false,"adx":40.7,"diP":34.7,"diN":16.8,"volVs65":0.31,"c1W":0.66,"c1M":18.51},"ARM":{"symbol":"ARM","name":"Arm Holdings plc","price":211.98,"change":-16.525,"changePercent":-7.2319,"volume":5271150,"avgVolume":7772946,"score":3.5,"signal":"BUY","rsi":56.0,"macd":14.534,"macdSig":16.2154,"macdHist":-1.6815,"macdUp":false,"macdDn":false,"sma20":209.13,"sma50":167.87,"ema50":178.39,"ema200":148.62,"goldenCross":false,"deathCross":false,"adx":34.3,"diP":29.7,"diN":17.7,"volVs65":0.68,"c1W":-0.61,"c1M":30.58},"TSM":{"symbol":"TSM","name":"Taiwan Semiconductor Manufactur","price":406.61,"change":-11.11,"changePercent":-2.6597,"volume":6353191,"avgVolume":13481281,"score":3.0,"signal":"BUY","rsi":57.4,"macd":11.5507,"macdSig":12.4021,"macdHist":-0.8514,"macdUp":false,"macdDn":false,"sma20":397.95,"sma50":367.5,"ema50":376.78,"ema200":319.72,"goldenCross":false,"deathCross":false,"adx":23.5,"diP":28.2,"diN":17.2,"volVs65":0.46,"c1W":-1.23,"c1M":11.91},"SMCI":{"symbol":"SMCI","name":"Super Micro Computer, Inc.","price":30.96,"change":-2.07,"changePercent":-6.267,"volume":14511436,"avgVolume":36871774,"score":0.0,"signal":"HOLD","rsi":53.4,"macd":1.5626,"macdSig":1.3716,"macdHist":0.191,"macdUp":false,"macdDn":false,"sma20":29.99,"sma50":27.78,"ema50":29.23,"ema200":34.46,"goldenCross":false,"deathCross":false,"adx":21.6,"diP":29.4,"diN":19.6,"volVs65":0.39,"c1W":-12.47,"c1M":9.01},"COHR":{"symbol":"COHR","name":"Coherent Corp.","price":385.95,"change":-18.985,"changePercent":-4.6884,"volume":3603576,"avgVolume":7400011,"score":4.5,"signal":"BUY","rsi":64.2,"macd":25.2062,"macdSig":20.321,"macdHist":4.8852,"macdUp":false,"macdDn":false,"sma20":345.41,"sma50":298.13,"ema50":308.7,"ema200":214.49,"goldenCross":false,"deathCross":false,"adx":26.6,"diP":29.6,"diN":15.9,"volVs65":0.48,"c1W":15.12,"c1M":17.67},"MSFT":{"symbol":"MSFT","name":"Microsoft Corporation","price":422.39,"change":12.96,"changePercent":3.1654,"volume":23273250,"avgVolume":33826868,"score":-1.0,"signal":"HOLD","rsi":58.1,"macd":3.422,"macdSig":4.7081,"macdHist":-1.2861,"macdUp":false,"macdDn":false,"sma20":417.43,"sma50":399.07,"ema50":408.98,"ema200":440.77,"goldenCross":false,"deathCross":false,"adx":16.1,"diP":33.7,"diN":25.4,"volVs65":0.68,"c1W":1.75,"c1M":0.51},"GOOGL":{"symbol":"GOOGL","name":"Alphabet Inc.","price":396.1,"change":-4.97,"changePercent":-1.2392,"volume":9040589,"avgVolume":29374424,"score":4.5,"signal":"BUY","rsi":69.7,"macd":20.0798,"macdSig":19.7335,"macdHist":0.3463,"macdUp":false,"macdDn":false,"sma20":372.86,"sma50":332.72,"ema50":347.61,"ema200":293.94,"goldenCross":false,"deathCross":false,"adx":48.6,"diP":38.7,"diN":14.0,"volVs65":0.3,"c1W":-1.17,"c1M":17.88},"META":{"symbol":"META","name":"Meta Platforms, Inc.","price":613.4,"change":-5.035,"changePercent":-0.8142,"volume":5524130,"avgVolume":15164365,"score":-2.0,"signal":"HOLD","rsi":45.3,"macd":-6.5727,"macdSig":-3.654,"macdHist":-2.9186,"macdUp":false,"macdDn":false,"sma20":634.67,"sma50":621.79,"ema50":628.84,"ema200":652.3,"goldenCross":false,"deathCross":false,"adx":20.7,"diP":24.3,"diN":32.2,"volVs65":0.36,"c1W":0.62,"c1M":-9.38},"AAPL":{"symbol":"AAPL","name":"Apple Inc.","price":301.24,"change":3.035,"changePercent":1.0177,"volume":22463894,"avgVolume":44058995,"score":2.0,"signal":"HOLD","rsi":76.6,"macd":9.5982,"macdSig":7.7573,"macdHist":1.8409,"macdUp":false,"macdDn":false,"sma20":281.41,"sma50":265.99,"ema50":272.84,"ema200":256.64,"goldenCross":false,"deathCross":false,"adx":29.6,"diP":38.4,"diN":11.5,"volVs65":0.5,"c1W":2.8,"c1M":14.47},"ORCL":{"symbol":"ORCL","name":"Oracle Corporation","price":192.36,"change":-3.25,"changePercent":-1.6615,"volume":7396693,"avgVolume":27379033,"score":0.5,"signal":"HOLD","rsi":62.0,"macd":8.8176,"macdSig":8.2772,"macdHist":0.5404,"macdUp":false,"macdDn":false,"sma20":182.02,"sma50":163.72,"ema50":171.92,"ema200":186.28,"goldenCross":false,"deathCross":false,"adx":30.1,"diP":33.8,"diN":16.1,"volVs65":0.27,"c1W":-1.83,"c1M":7.86},"ADBE":{"symbol":"ADBE","name":"Adobe Inc.","price":244.64,"change":7.63,"changePercent":3.2193,"volume":2328639,"avgVolume":5568728,"score":-2.0,"signal":"HOLD","rsi":48.8,"macd":-1.1944,"macdSig":-0.3847,"macdHist":-0.8097,"macdUp":false,"macdDn":false,"sma20":246.65,"sma50":247.47,"ema50":251.59,"ema200":300.32,"goldenCross":false,"deathCross":false,"adx":14.2,"diP":21.9,"diN":23.4,"volVs65":0.41,"c1W":-3.32,"c1M":-1.42},"CRM":{"symbol":"CRM","name":"Salesforce, Inc.","price":173.7,"change":6.12,"changePercent":3.652,"volume":5281737,"avgVolume":13352259,"score":-2.0,"signal":"HOLD","rsi":44.9,"macd":-3.1224,"macdSig":-2.0111,"macdHist":-1.1113,"macdUp":false,"macdDn":false,"sma20":179.77,"sma50":183.61,"ema50":184.74,"ema200":218.4,"goldenCross":false,"deathCross":false,"adx":15.3,"diP":21.1,"diN":30.7,"volVs65":0.39,"c1W":-4.47,"c1M":-4.15},"NOW":{"symbol":"NOW","name":"ServiceNow, Inc.","price":94.92,"change":4.4236,"changePercent":4.888,"volume":17261168,"avgVolume":22146105,"score":-1.0,"signal":"HOLD","rsi":51.9,"macd":-2.0623,"macdSig":-2.7989,"macdHist":0.7365,"macdUp":false,"macdDn":false,"sma20":91.9,"sma50":99.73,"ema50":99.15,"ema200":136.41,"goldenCross":false,"deathCross":false,"adx":18.4,"diP":29.4,"diN":27.7,"volVs65":0.77,"c1W":4.11,"c1M":-1.57},"PANW":{"symbol":"PANW","name":"Palo Alto Networks, Inc.","price":239.51,"change":1.3013,"changePercent":0.5463,"volume":4684671,"avgVolume":9403119,"score":3.5,"signal":"BUY","rsi":85.4,"macd":16.4782,"macdSig":11.0008,"macdHist":5.4774,"macdUp":false,"macdDn":false,"sma20":193.74,"sma50":175.53,"ema50":183.37,"ema200":183.11,"goldenCross":true,"deathCross":false,"adx":31.0,"diP":47.0,"diN":9.5,"volVs65":0.47,"c1W":15.22,"c1M":43.45},"CRWD":{"symbol":"CRWD","name":"CrowdStrike Holdings, Inc.","price":586.47,"change":6.525,"changePercent":1.1251,"volume":1355247,"avgVolume":3935342,"score":3.5,"signal":"BUY","rsi":81.8,"macd":39.1998,"macdSig":27.8493,"macdHist":11.3505,"macdUp":false,"macdDn":false,"sma20":488.55,"sma50":442.39,"ema50":461.09,"ema200":453.87,"goldenCross":true,"deathCross":false,"adx":29.0,"diP":43.3,"diN":11.1,"volVs65":0.34,"c1W":11.12,"c1M":40.24},"INTU":{"symbol":"INTU","name":"Intuit Inc.","price":392.79,"change":14.5,"changePercent":3.833,"volume":1083153,"avgVolume":3629808,"score":-2.0,"signal":"HOLD","rsi":48.7,"macd":-5.5916,"macdSig":-5.4991,"macdHist":-0.0924,"macdUp":false,"macdDn":false,"sma20":394.56,"sma50":411.3,"ema50":412.42,"ema200":528.74,"goldenCross":false,"deathCross":false,"adx":12.1,"diP":23.5,"diN":28.8,"volVs65":0.29,"c1W":-0.89,"c1M":1.47},"SNOW":{"symbol":"SNOW","name":"Snowflake Inc.","price":157.46,"change":6.7,"changePercent":4.4442,"volume":3268085,"avgVolume":6822578,"score":0.0,"signal":"HOLD","rsi":58.0,"macd":0.5709,"macdSig":-1.4737,"macdHist":2.0446,"macdUp":false,"macdDn":false,"sma20":147.25,"sma50":154.18,"ema50":155.59,"ema200":187.36,"goldenCross":false,"deathCross":false,"adx":13.9,"diP":26.8,"diN":23.8,"volVs65":0.48,"c1W":3.29,"c1M":9.69},"PLTR":{"symbol":"PLTR","name":"Palantir Technologies Inc.","price":133.84,"change":0.11,"changePercent":0.0823,"volume":15839123,"avgVolume":48669943,"score":-2.0,"signal":"HOLD","rsi":43.3,"macd":-2.8206,"macdSig":-2.2488,"macdHist":-0.5717,"macdUp":false,"macdDn":false,"sma20":139.78,"sma50":144.4,"ema50":142.8,"ema200":152.66,"goldenCross":false,"deathCross":false,"adx":12.3,"diP":20.7,"diN":28.9,"volVs65":0.32,"c1W":-2.87,"c1M":-6.25},"SHOP":{"symbol":"SHOP","name":"Shopify Inc.","price":99.78,"change":2.36,"changePercent":2.4225,"volume":7706731,"avgVolume":11072332,"score":-2.0,"signal":"HOLD","rsi":36.5,"macd":-6.4168,"macdSig":-4.0244,"macdHist":-2.3924,"macdUp":false,"macdDn":false,"sma20":116.12,"sma50":119.17,"ema50":118.49,"ema200":130.42,"goldenCross":false,"deathCross":false,"adx":22.5,"diP":18.0,"diN":37.1,"volVs65":0.65,"c1W":-9.63,"c1M":-21.4},"SPOT":{"symbol":"SPOT","name":"Spotify Technology S.A.","price":436.22,"change":3.68,"changePercent":0.8508,"volume":717551,"avgVolume":2237816,"score":-2.5,"signal":"HOLD","rsi":40.3,"macd":-18.2937,"macdSig":-17.7453,"macdHist":-0.5484,"macdUp":false,"macdDn":false,"sma20":457.89,"sma50":484.19,"ema50":474.86,"ema200":550.75,"goldenCross":false,"deathCross":false,"adx":30.8,"diP":17.4,"diN":28.2,"volVs65":0.31,"c1W":4.4,"c1M":-17.92},"RDDT":{"symbol":"RDDT","name":"Reddit, Inc.","price":155.66,"change":-0.65,"changePercent":-0.4158,"volume":1340803,"avgVolume":4939427,"score":-1.0,"signal":"HOLD","rsi":50.1,"macd":1.8446,"macdSig":3.078,"macdHist":-1.2334,"macdUp":false,"macdDn":false,"sma20":158.49,"sma50":147.54,"ema50":155.74,"ema200":169.71,"goldenCross":false,"deathCross":false,"adx":14.1,"diP":24.4,"diN":21.0,"volVs65":0.27,"c1W":-0.09,"c1M":-4.18},"EQIX":{"symbol":"EQIX","name":"Equinix, Inc.","price":1063.43,"change":-16.25,"changePercent":-1.5051,"volume":104765,"avgVolume":632797,"score":3.0,"signal":"BUY","rsi":49.5,"macd":11.1828,"macdSig":17.4355,"macdHist":-6.2527,"macdUp":false,"macdDn":false,"sma20":1086.18,"sma50":1030.79,"ema50":1029.92,"ema200":904.23,"goldenCross":false,"deathCross":false,"adx":22.1,"diP":16.9,"diN":23.4,"volVs65":0.16,"c1W":-0.81,"c1M":-0.7},"NBIS":{"symbol":"NBIS","name":"Nebius Group N.V.","price":212.8,"change":-8.35,"changePercent":-3.7757,"volume":12233297,"avgVolume":16904389,"score":4.5,"signal":"BUY","rsi":68.3,"macd":19.3219,"macdSig":15.3129,"macdHist":4.0091,"macdUp":false,"macdDn":false,"sma20":170.31,"sma50":140.47,"ema50":149.02,"ema200":107.5,"goldenCross":false,"deathCross":false,"adx":38.4,"diP":40.3,"diN":8.4,"volVs65":0.72,"c1W":20.19,"c1M":28.7},"CRWV":{"symbol":"CRWV","name":"CoreWeave, Inc.","price":108.21,"change":-6.005,"changePercent":-5.2576,"volume":10600895,"avgVolume":27842672,"score":4.5,"signal":"BUY","rsi":47.7,"macd":3.1887,"macdSig":5.694,"macdHist":-2.5053,"macdUp":false,"macdDn":false,"sma20":116.78,"sma50":99.21,"ema50":105.04,"ema200":97.93,"goldenCross":true,"deathCross":false,"adx":17.5,"diP":24.1,"diN":26.9,"volVs65":0.38,"c1W":-5.2,"c1M":-9.49},"OKLO":{"symbol":"OKLO","name":"Oklo Inc.","price":61.96,"change":-5.25,"changePercent":-7.8113,"volume":5864125,"avgVolume":10899925,"score":-0.5,"signal":"HOLD","rsi":44.9,"macd":1.9543,"macdSig":3.2099,"macdHist":-1.2555,"macdUp":false,"macdDn":false,"sma20":70.75,"sma50":61.46,"ema50":66.64,"ema200":73.42,"goldenCross":false,"deathCross":false,"adx":27.4,"diP":24.0,"diN":19.0,"volVs65":0.54,"c1W":-14.55,"c1M":-3.5},"SOUN":{"symbol":"SOUN","name":"SoundHound AI, Inc.","price":8.38,"change":-0.145,"changePercent":-1.7019,"volume":7891740,"avgVolume":27760692,"score":-0.5,"signal":"HOLD","rsi":51.3,"macd":0.2617,"macdSig":0.3492,"macdHist":-0.0875,"macdUp":false,"macdDn":false,"sma20":8.51,"sma50":7.64,"ema50":8.19,"ema200":10.07,"goldenCross":false,"deathCross":false,"adx":25.9,"diP":26.9,"diN":20.5,"volVs65":0.28,"c1W":-5.69,"c1M":8.77},"BBAI":{"symbol":"BBAI","name":"BigBear.ai, Inc.","price":4.16,"change":-0.215,"changePercent":-4.9087,"volume":16435340,"avgVolume":36129029,"score":0.5,"signal":"HOLD","rsi":54.0,"macd":0.1382,"macdSig":0.1242,"macdHist":0.0139,"macdUp":false,"macdDn":false,"sma20":4.06,"sma50":3.82,"ema50":4.05,"ema200":4.79,"goldenCross":false,"deathCross":false,"adx":28.8,"diP":25.9,"diN":12.0,"volVs65":0.45,"c1W":-0.36,"c1M":11.07},"JPM":{"symbol":"JPM","name":"JP Morgan Chase & Co.","price":297.27,"change":-2.64,"changePercent":-0.8803,"volume":2940478,"avgVolume":9442596,"score":2.0,"signal":"HOLD","rsi":41.3,"macd":-0.9515,"macdSig":0.9919,"macdHist":-1.9434,"macdUp":false,"macdDn":false,"sma20":308.18,"sma50":299.67,"ema50":303.82,"ema200":298.73,"goldenCross":false,"deathCross":false,"adx":18.2,"diP":17.1,"diN":27.6,"volVs65":0.31,"c1W":-1.6,"c1M":-4.09},"BAC":{"symbol":"BAC","name":"Bank of America Corporation","price":49.47,"change":-0.375,"changePercent":-0.7523,"volume":14146326,"avgVolume":38591715,"score":2.0,"signal":"HOLD","rsi":36.3,"macd":-0.3763,"macdSig":0.1262,"macdHist":-0.5025,"macdUp":false,"macdDn":false,"sma20":52.17,"sma50":50.53,"ema50":51.44,"ema200":50.53,"goldenCross":false,"deathCross":false,"adx":21.3,"diP":19.1,"diN":30.7,"volVs65":0.36,"c1W":-3.58,"c1M":-7.54},"C":{"symbol":"C","name":"Citigroup, Inc.","price":123.13,"change":-1.69,"changePercent":-1.354,"volume":2180250,"avgVolume":13744330,"score":3.0,"signal":"BUY","rsi":45.6,"macd":0.8188,"macdSig":1.8427,"macdHist":-1.0239,"macdUp":false,"macdDn":false,"sma20":127.29,"sma50":119.65,"ema50":121.94,"ema200":108.64,"goldenCross":false,"deathCross":false,"adx":16.5,"diP":20.4,"diN":18.3,"volVs65":0.16,"c1W":-1.93,"c1M":-4.35},"GS":{"symbol":"GS","name":"Goldman Sachs Group, Inc. (The)","price":952.16,"change":-16.8,"changePercent":-1.7338,"volume":810687,"avgVolume":2180658,"score":4.0,"signal":"BUY","rsi":59.4,"macd":17.3777,"macdSig":16.1092,"macdHist":1.2685,"macdUp":false,"macdDn":false,"sma20":933.4,"sma50":881.27,"ema50":905.95,"ema200":835.35,"goldenCross":false,"deathCross":false,"adx":15.9,"diP":26.6,"diN":20.9,"volVs65":0.37,"c1W":1.67,"c1M":5.8},"AXP":{"symbol":"AXP","name":"American Express Company","price":313.2,"change":0.43,"changePercent":0.1375,"volume":954704,"avgVolume":3655178,"score":-2.0,"signal":"HOLD","rsi":46.6,"macd":-0.9707,"macdSig":0.2134,"macdHist":-1.1841,"macdUp":false,"macdDn":false,"sma20":318.61,"sma50":311.0,"ema50":318.49,"ema200":326.85,"goldenCross":false,"deathCross":false,"adx":14.8,"diP":21.6,"diN":22.3,"volVs65":0.26,"c1W":-0.9,"c1M":-3.86},"MA":{"symbol":"MA","name":"Mastercard Incorporated","price":496.84,"change":6.8999,"changePercent":1.4083,"volume":1428919,"avgVolume":3583778,"score":-2.0,"signal":"HOLD","rsi":47.1,"macd":-3.5379,"macdSig":-2.5155,"macdHist":-1.0225,"macdUp":false,"macdDn":false,"sma20":502.38,"sma50":502.59,"ema50":506.36,"ema200":534.37,"goldenCross":false,"deathCross":false,"adx":13.5,"diP":21.5,"diN":24.6,"volVs65":0.39,"c1W":0.27,"c1M":-4.18},"V":{"symbol":"V","name":"Visa Inc.","price":326.29,"change":3.765,"changePercent":1.1674,"volume":2686540,"avgVolume":7369789,"score":0.5,"signal":"HOLD","rsi":58.5,"macd":3.5533,"macdSig":3.4417,"macdHist":0.1115,"macdUp":true,"macdDn":false,"sma20":319.09,"sma50":311.27,"ema50":316.6,"ema200":328.21,"goldenCross":false,"deathCross":false,"adx":18.1,"diP":33.5,"diN":21.9,"volVs65":0.36,"c1W":2.56,"c1M":3.76},"PYPL":{"symbol":"PYPL","name":"PayPal Holdings, Inc.","price":44.86,"change":-0.18,"changePercent":-0.3996,"volume":6349820,"avgVolume":19029351,"score":-2.0,"signal":"HOLD","rsi":36.7,"macd":-0.7445,"macdSig":-0.1664,"macdHist":-0.5781,"macdUp":false,"macdDn":false,"sma20":48.25,"sma50":46.77,"ema50":47.53,"ema200":55.4,"goldenCross":false,"deathCross":false,"adx":24.4,"diP":16.9,"diN":28.9,"volVs65":0.33,"c1W":-1.12,"c1M":-9.94},"COF":{"symbol":"COF","name":"Capital One Financial Corporati","price":186.26,"change":0.47,"changePercent":0.253,"volume":1061793,"avgVolume":4917738,"score":-2.0,"signal":"HOLD","rsi":43.9,"macd":-2.2122,"macdSig":-1.24,"macdHist":-0.9721,"macdUp":false,"macdDn":false,"sma20":191.61,"sma50":188.55,"ema50":193.22,"ema200":204.98,"goldenCross":false,"deathCross":false,"adx":14.8,"diP":20.4,"diN":26.9,"volVs65":0.21,"c1W":-1.7,"c1M":-7.2},"BLK":{"symbol":"BLK","name":"BlackRock, Inc.","price":1086.12,"change":-17.91,"changePercent":-1.6222,"volume":125250,"avgVolume":790713,"score":0.0,"signal":"HOLD","rsi":59.7,"macd":20.1838,"macdSig":18.5349,"macdHist":1.6489,"macdUp":false,"macdDn":false,"sma20":1065.54,"sma50":1011.56,"ema50":1043.84,"ema200":1046.44,"goldenCross":false,"deathCross":false,"adx":18.1,"diP":24.7,"diN":17.4,"volVs65":0.16,"c1W":0.12,"c1M":5.97},"SPGI":{"symbol":"SPGI","name":"S&P Global Inc.","price":404.35,"change":0.425,"changePercent":0.1052,"volume":573022,"avgVolume":2214528,"score":-2.0,"signal":"HOLD","rsi":33.0,"macd":-6.1329,"macdSig":-3.1839,"macdHist":-2.9491,"macdUp":false,"macdDn":false,"sma20":427.72,"sma50":427.36,"ema50":431.39,"ema200":469.57,"goldenCross":false,"deathCross":false,"adx":11.2,"diP":18.7,"diN":26.4,"volVs65":0.25,"c1W":-3.75,"c1M":-7.43},"SOFI":{"symbol":"SOFI","name":"SoFi Technologies, Inc.","price":15.54,"change":-0.4816,"changePercent":-3.0062,"volume":23735223,"avgVolume":65388837,"score":-2.0,"signal":"HOLD","rsi":40.7,"macd":-0.5392,"macdSig":-0.4265,"macdHist":-0.1126,"macdUp":false,"macdDn":false,"sma20":16.93,"sma50":17.05,"ema50":17.56,"ema200":20.5,"goldenCross":false,"deathCross":false,"adx":21.9,"diP":19.8,"diN":27.4,"volVs65":0.36,"c1W":-1.34,"c1M":-18.35},"HOOD":{"symbol":"HOOD","name":"Robinhood Markets, Inc.","price":76.78,"change":-3.9201,"changePercent":-4.8576,"volume":9601862,"avgVolume":29575714,"score":-2.0,"signal":"HOLD","rsi":47.9,"macd":-0.0302,"macdSig":0.1632,"macdHist":-0.1934,"macdUp":false,"macdDn":false,"sma20":79.87,"sma50":76.47,"ema50":79.71,"ema200":91.55,"goldenCross":false,"deathCross":false,"adx":14.5,"diP":27.2,"diN":21.3,"volVs65":0.31,"c1W":-0.32,"c1M":-11.59},"COIN":{"symbol":"COIN","name":"Coinbase Global, Inc.","price":192.96,"change":-19.055,"changePercent":-8.9878,"volume":7628664,"avgVolume":11925834,"score":0.0,"signal":"HOLD","rsi":48.2,"macd":3.9687,"macdSig":3.9121,"macdHist":0.0566,"macdUp":false,"macdDn":false,"sma20":199.34,"sma50":191.68,"ema50":195.61,"ema200":232.07,"goldenCross":false,"deathCross":false,"adx":13.8,"diP":27.7,"diN":17.3,"volVs65":0.63,"c1W":-4.08,"c1M":-3.44},"MSTR":{"symbol":"MSTR","name":"Strategy Inc","price":174.89,"change":-12.08,"changePercent":-6.4609,"volume":9419362,"avgVolume":18890571,"score":-0.5,"signal":"HOLD","rsi":53.0,"macd":9.5457,"macdSig":10.7043,"macdHist":-1.1587,"macdUp":false,"macdDn":false,"sma20":176.93,"sma50":152.09,"ema50":161.24,"ema200":211.31,"goldenCross":false,"deathCross":false,"adx":30.3,"diP":30.2,"diN":14.2,"volVs65":0.49,"c1W":-6.77,"c1M":17.42},"RIOT":{"symbol":"RIOT","name":"Riot Platforms, Inc.","price":23.35,"change":-1.27,"changePercent":-5.1584,"volume":6057502,"avgVolume":18477083,"score":4.5,"signal":"BUY","rsi":63.8,"macd":2.2411,"macdSig":1.9187,"macdHist":0.3223,"macdUp":false,"macdDn":false,"sma20":20.55,"sma50":17.08,"ema50":18.54,"ema200":15.73,"goldenCross":false,"deathCross":false,"adx":27.6,"diP":35.0,"diN":17.3,"volVs65":0.32,"c1W":-3.03,"c1M":38.0},"MARA":{"symbol":"MARA","name":"MARA Holdings, Inc.","price":12.26,"change":-1.0299,"changePercent":-7.7494,"volume":19421569,"avgVolume":46614424,"score":-1.0,"signal":"HOLD","rsi":55.0,"macd":0.7464,"macdSig":0.7781,"macdHist":-0.0317,"macdUp":false,"macdDn":true,"sma20":12.08,"sma50":10.29,"ema50":10.94,"ema200":12.05,"goldenCross":false,"deathCross":false,"adx":29.5,"diP":28.2,"diN":15.7,"volVs65":0.41,"c1W":-5.25,"c1M":6.15},"IREN":{"symbol":"IREN","name":"IREN LIMITED","price":53.57,"change":-4.83,"changePercent":-8.2706,"volume":23178168,"avgVolume":38548591,"score":4.0,"signal":"BUY","rsi":53.9,"macd":3.5437,"macdSig":3.4311,"macdHist":0.1126,"macdUp":false,"macdDn":false,"sma20":51.69,"sma50":44.73,"ema50":47.8,"ema200":40.71,"goldenCross":false,"deathCross":false,"adx":23.1,"diP":28.3,"diN":15.9,"volVs65":0.6,"c1W":-12.47,"c1M":12.31},"FUTU":{"symbol":"FUTU","name":"Futu Holdings Limited","price":134.27,"change":-7.235,"changePercent":-5.1127,"volume":1026618,"avgVolume":1590894,"score":-2.0,"signal":"HOLD","rsi":37.1,"macd":-3.325,"macdSig":-0.6838,"macdHist":-2.6412,"macdUp":false,"macdDn":false,"sma20":152.31,"sma50":147.56,"ema50":149.96,"ema200":150.98,"goldenCross":true,"deathCross":true,"adx":19.3,"diP":17.9,"diN":32.3,"volVs65":0.64,"c1W":-7.13,"c1M":-18.65},"UNH":{"symbol":"UNH","name":"UnitedHealth Group Incorporated","price":392.71,"change":-6.38,"changePercent":-1.5986,"volume":3008547,"avgVolume":8409917,"score":3.5,"signal":"BUY","rsi":75.8,"macd":21.6147,"macdSig":20.8037,"macdHist":0.811,"macdUp":false,"macdDn":false,"sma20":369.47,"sma50":320.21,"ema50":337.89,"ema200":313.99,"goldenCross":true,"deathCross":false,"adx":55.6,"diP":41.5,"diN":10.5,"volVs65":0.36,"c1W":3.35,"c1M":24.12},"JNJ":{"symbol":"JNJ","name":"Johnson & Johnson","price":228.31,"change":-2.49,"changePercent":-1.0789,"volume":2811405,"avgVolume":7966509,"score":3.0,"signal":"BUY","rsi":48.2,"macd":-2.1441,"macdSig":-3.0183,"macdHist":0.8743,"macdUp":false,"macdDn":false,"sma20":226.6,"sma50":234.54,"ema50":230.9,"ema200":210.49,"goldenCross":false,"deathCross":false,"adx":19.6,"diP":22.6,"diN":24.2,"volVs65":0.35,"c1W":3.16,"c1M":-2.66},"LLY":{"symbol":"LLY","name":"Eli Lilly and Company","price":1004.45,"change":-2.255,"changePercent":-0.224,"volume":908754,"avgVolume":3060068,"score":4.0,"signal":"BUY","rsi":60.7,"macd":19.3928,"macdSig":10.2932,"macdHist":9.0996,"macdUp":false,"macdDn":false,"sma20":944.42,"sma50":940.16,"ema50":956.54,"ema200":925.47,"goldenCross":false,"deathCross":false,"adx":18.5,"diP":29.7,"diN":19.2,"volVs65":0.29,"c1W":5.9,"c1M":11.11},"MRK":{"symbol":"MRK","name":"Merck & Company, Inc.","price":111.62,"change":-1.79,"changePercent":-1.5783,"volume":2752367,"avgVolume":9545233,"score":3.0,"signal":"BUY","rsi":43.3,"macd":-1.1037,"macdSig":-1.3308,"macdHist":0.227,"macdUp":false,"macdDn":false,"sma20":112.36,"sma50":115.68,"ema50":114.32,"ema200":103.18,"goldenCross":false,"deathCross":false,"adx":23.7,"diP":13.2,"diN":24.1,"volVs65":0.28,"c1W":0.22,"c1M":-3.33},"ABBV":{"symbol":"ABBV","name":"AbbVie Inc.","price":210.46,"change":-0.31,"changePercent":-0.1471,"volume":1796973,"avgVolume":6768838,"score":-1.5,"signal":"HOLD","rsi":56.0,"macd":0.0437,"macdSig":-1.0892,"macdHist":1.1329,"macdUp":false,"macdDn":false,"sma20":204.49,"sma50":208.8,"ema50":209.2,"ema200":210.02,"goldenCross":false,"deathCross":true,"adx":16.7,"diP":31.7,"diN":16.7,"volVs65":0.26,"c1W":4.42,"c1M":0.7},"NVO":{"symbol":"NVO","name":"Novo Nordisk A/S","price":44.49,"change":-1.305,"changePercent":-2.8493,"volume":8469418,"avgVolume":19765941,"score":0.5,"signal":"HOLD","rsi":58.4,"macd":1.8747,"macdSig":1.79,"macdHist":0.0846,"macdUp":false,"macdDn":false,"sma20":43.26,"sma50":39.55,"ema50":42.19,"ema200":47.76,"goldenCross":false,"deathCross":false,"adx":31.2,"diP":38.9,"diN":24.8,"volVs65":0.43,"c1W":-3.42,"c1M":8.71},"ISRG":{"symbol":"ISRG","name":"Intuitive Surgical, Inc.","price":423.5,"change":-4.56,"changePercent":-1.0653,"volume":791300,"avgVolume":1933556,"score":-2.0,"signal":"HOLD","rsi":34.4,"macd":-10.7831,"macdSig":-7.7078,"macdHist":-3.0752,"macdUp":false,"macdDn":false,"sma20":453.16,"sma50":462.91,"ema50":463.62,"ema200":498.73,"goldenCross":false,"deathCross":false,"adx":24.5,"diP":14.0,"diN":33.1,"volVs65":0.41,"c1W":-5.9,"c1M":-7.55},"HIMS":{"symbol":"HIMS","name":"Hims & Hers Health, Inc.","price":24.91,"change":0.6693,"changePercent":2.7611,"volume":10775373,"avgVolume":35562388,"score":-1.5,"signal":"HOLD","rsi":47.6,"macd":0.2925,"macdSig":0.8921,"macdHist":-0.5996,"macdUp":false,"macdDn":false,"sma20":27.43,"sma50":24.16,"ema50":25.1,"ema200":33.67,"goldenCross":false,"deathCross":false,"adx":25.4,"diP":24.5,"diN":24.6,"volVs65":0.3,"c1W":-11.89,"c1M":-7.71},"AMZN":{"symbol":"AMZN","name":"Amazon.com, Inc.","price":262.2,"change":-5.025,"changePercent":-1.8805,"volume":19299284,"avgVolume":47292115,"score":3.5,"signal":"BUY","rsi":56.1,"macd":8.6086,"macdSig":10.757,"macdHist":-2.1484,"macdUp":false,"macdDn":false,"sma20":264.43,"sma50":236.67,"ema50":245.89,"ema200":229.47,"goldenCross":false,"deathCross":false,"adx":38.4,"diP":27.2,"diN":20.5,"volVs65":0.4,"c1W":-3.85,"c1M":5.0},"TSLA":{"symbol":"TSLA","name":"Tesla, Inc.","price":425.17,"change":-18.126,"changePercent":-4.0889,"volume":25875997,"avgVolume":61909555,"score":6.0,"signal":"BUY","rsi":59.3,"macd":15.551,"macdSig":10.7772,"macdHist":4.7738,"macdUp":false,"macdDn":false,"sma20":401.47,"sma50":386.84,"ema50":398.28,"ema200":397.22,"goldenCross":true,"deathCross":false,"adx":26.2,"diP":29.8,"diN":17.4,"volVs65":0.41,"c1W":-0.74,"c1M":9.33},"HD":{"symbol":"HD","name":"Home Depot, Inc. (The)","price":299.48,"change":-4.87,"changePercent":-1.6001,"volume":2064602,"avgVolume":4098304,"score":-2.5,"signal":"HOLD","rsi":31.1,"macd":-8.9445,"macdSig":-6.7536,"macdHist":-2.1909,"macdUp":false,"macdDn":false,"sma20":323.33,"sma50":330.68,"ema50":331.86,"ema200":354.5,"goldenCross":false,"deathCross":false,"adx":29.7,"diP":13.9,"diN":39.3,"volVs65":0.5,"c1W":-5.66,"c1M":-11.17},"MCD":{"symbol":"MCD","name":"McDonald's Corporation","price":276.14,"change":1.1701,"changePercent":0.4255,"volume":1252153,"avgVolume":3464857,"score":-5.0,"signal":"SELL","rsi":28.6,"macd":-8.4763,"macdSig":-7.8698,"macdHist":-0.6065,"macdUp":false,"macdDn":false,"sma20":287.64,"sma50":302.96,"ema50":298.06,"ema200":305.69,"goldenCross":false,"deathCross":true,"adx":30.7,"diP":14.2,"diN":29.7,"volVs65":0.36,"c1W":0.14,"c1M":-10.04},"NKE":{"symbol":"NKE","name":"Nike, Inc.","price":42.47,"change":0.45,"changePercent":1.0709,"volume":9144588,"avgVolume":20881092,"score":-1.5,"signal":"HOLD","rsi":34.5,"macd":-1.4845,"macdSig":-1.5928,"macdHist":0.1083,"macdUp":false,"macdDn":false,"sma20":44.07,"sma50":47.61,"ema50":47.83,"ema200":57.68,"goldenCross":false,"deathCross":false,"adx":36.4,"diP":15.6,"diN":35.6,"volVs65":0.44,"c1W":-3.78,"c1M":-7.07},"SBUX":{"symbol":"SBUX","name":"Starbucks Corporation","price":106.23,"change":-0.17,"changePercent":-0.1598,"volume":2843520,"avgVolume":7713343,"score":4.5,"signal":"BUY","rsi":63.9,"macd":2.4759,"macdSig":2.4343,"macdHist":0.0416,"macdUp":false,"macdDn":false,"sma20":103.14,"sma50":98.53,"ema50":99.75,"ema200":92.58,"goldenCross":false,"deathCross":false,"adx":27.6,"diP":30.8,"diN":17.0,"volVs65":0.37,"c1W":1.24,"c1M":8.0},"CVNA":{"symbol":"CVNA","name":"Carvana Co.","price":68.43,"change":-1.1,"changePercent":-1.582,"volume":4206826,"avgVolume":16170300,"score":3.5,"signal":"BUY","rsi":38.4,"macd":-0.0842,"macdSig":1.5673,"macdHist":-1.6515,"macdUp":false,"macdDn":false,"sma20":77.44,"sma50":69.34,"ema50":72.97,"ema200":72.13,"goldenCross":true,"deathCross":false,"adx":17.6,"diP":15.7,"diN":27.8,"volVs65":0.25,"c1W":-12.2,"c1M":-5.55},"RIVN":{"symbol":"RIVN","name":"Rivian Automotive, Inc.","price":13.85,"change":-0.665,"changePercent":-4.5799,"volume":21797544,"avgVolume":29136248,"score":-3.5,"signal":"SELL","rsi":36.6,"macd":-0.5134,"macdSig":-0.3545,"macdHist":-0.159,"macdUp":false,"macdDn":false,"sma20":15.41,"sma50":15.52,"ema50":15.42,"ema200":15.52,"goldenCross":false,"deathCross":true,"adx":17.5,"diP":20.2,"diN":30.3,"volVs65":0.75,"c1W":-2.57,"c1M":-17.97},"ABNB":{"symbol":"ABNB","name":"Airbnb, Inc.","price":132.41,"change":-1.26,"changePercent":-0.9426,"volume":934242,"avgVolume":4203020,"score":2.0,"signal":"HOLD","rsi":40.7,"macd":-0.031,"macdSig":1.3053,"macdHist":-1.3364,"macdUp":false,"macdDn":false,"sma20":139.48,"sma50":133.95,"ema50":134.92,"ema200":131.32,"goldenCross":false,"deathCross":false,"adx":14.2,"diP":20.5,"diN":20.7,"volVs65":0.22,"c1W":-6.42,"c1M":-3.92},"CPNG":{"symbol":"CPNG","name":"Coupang, Inc.","price":16.12,"change":-0.47,"changePercent":-2.833,"volume":4169401,"avgVolume":22840193,"score":-2.5,"signal":"HOLD","rsi":30.5,"macd":-1.0256,"macdSig":-0.5979,"macdHist":-0.4277,"macdUp":false,"macdDn":false,"sma20":18.96,"sma50":19.25,"ema50":19.16,"ema200":22.89,"goldenCross":false,"deathCross":false,"adx":29.5,"diP":15.4,"diN":34.3,"volVs65":0.18,"c1W":-5.06,"c1M":-24.99},"MELI":{"symbol":"MELI","name":"MercadoLibre, Inc.","price":1555.54,"change":-51.83,"changePercent":-3.2245,"volume":240227,"avgVolume":585578,"score":-2.0,"signal":"HOLD","rsi":34.6,"macd":-55.2816,"macdSig":-25.1888,"macdHist":-30.0929,"macdUp":false,"macdDn":false,"sma20":1755.31,"sma50":1738.48,"ema50":1770.33,"ema200":2018.66,"goldenCross":false,"deathCross":false,"adx":21.4,"diP":21.8,"diN":36.7,"volVs65":0.41,"c1W":-4.72,"c1M":-14.63},"NFLX":{"symbol":"NFLX","name":"Netflix, Inc.","price":87.02,"change":0.08,"changePercent":0.092,"volume":14699692,"avgVolume":44175521,"score":-2.0,"signal":"HOLD","rsi":36.7,"macd":-2.4242,"macdSig":-2.0399,"macdHist":-0.3843,"macdUp":false,"macdDn":false,"sma20":90.24,"sma50":94.45,"ema50":92.28,"ema200":100.0,"goldenCross":false,"deathCross":false,"adx":21.1,"diP":20.9,"diN":27.2,"volVs65":0.33,"c1W":-0.54,"c1M":-19.27},"WMT":{"symbol":"WMT","name":"Walmart Inc.","price":131.24,"change":-1.22,"changePercent":-0.921,"volume":7614733,"avgVolume":19706288,"score":4.0,"signal":"BUY","rsi":56.6,"macd":1.3281,"macdSig":1.3023,"macdHist":0.0259,"macdUp":false,"macdDn":false,"sma20":129.88,"sma50":126.36,"ema50":127.07,"ema200":116.19,"goldenCross":false,"deathCross":false,"adx":9.8,"diP":25.2,"diN":21.7,"volVs65":0.38,"c1W":0.62,"c1M":5.34},"COST":{"symbol":"COST","name":"Costco Wholesale Corporation","price":1043.06,"change":1.8149,"changePercent":0.1743,"volume":834970,"avgVolume":1828359,"score":4.0,"signal":"BUY","rsi":64.1,"macd":9.4365,"macdSig":5.8163,"macdHist":3.6203,"macdUp":false,"macdDn":false,"sma20":1011.06,"sma50":1000.2,"ema50":1000.53,"ema200":971.32,"goldenCross":false,"deathCross":false,"adx":10.9,"diP":30.4,"diN":19.3,"volVs65":0.45,"c1W":3.4,"c1M":5.81},"KO":{"symbol":"KO","name":"Coca-Cola Company (The)","price":80.76,"change":0.315,"changePercent":0.3916,"volume":8235610,"avgVolume":15483566,"score":4.5,"signal":"BUY","rsi":67.3,"macd":1.0132,"macdSig":0.7394,"macdHist":0.2738,"macdUp":false,"macdDn":false,"sma20":78.03,"sma50":77.0,"ema50":77.3,"ema200":73.44,"goldenCross":false,"deathCross":false,"adx":25.9,"diP":30.7,"diN":12.1,"volVs65":0.52,"c1W":2.99,"c1M":7.43},"PG":{"symbol":"PG","name":"Procter & Gamble Company (The)","price":142.02,"change":-0.69,"changePercent":-0.4835,"volume":2842229,"avgVolume":10012714,"score":-2.0,"signal":"HOLD","rsi":42.8,"macd":-0.677,"macdSig":-0.2982,"macdHist":-0.3787,"macdUp":false,"macdDn":false,"sma20":145.03,"sma50":145.22,"ema50":145.87,"ema200":148.74,"goldenCross":false,"deathCross":false,"adx":17.7,"diP":20.6,"diN":27.5,"volVs65":0.28,"c1W":-3.01,"c1M":-0.01},"PM":{"symbol":"PM","name":"Philip Morris International Inc","price":191.01,"change":-0.845,"changePercent":-0.4404,"volume":1584757,"avgVolume":4906897,"score":2.0,"signal":"HOLD","rsi":74.6,"macd":6.6074,"macdSig":3.6944,"macdHist":2.9129,"macdUp":false,"macdDn":false,"sma20":171.01,"sma50":166.69,"ema50":169.94,"ema200":165.71,"goldenCross":false,"deathCross":false,"adx":34.6,"diP":42.2,"diN":9.5,"volVs65":0.32,"c1W":11.71,"c1M":22.26},"MO":{"symbol":"MO","name":"Altria Group, Inc.","price":72.44,"change":0.03,"changePercent":0.0414,"volume":3401022,"avgVolume":9325864,"score":4.0,"signal":"BUY","rsi":62.5,"macd":1.3908,"macdSig":1.2471,"macdHist":0.1438,"macdUp":false,"macdDn":false,"sma20":69.3,"sma50":67.04,"ema50":67.54,"ema200":62.66,"goldenCross":false,"deathCross":false,"adx":20.4,"diP":39.1,"diN":21.2,"volVs65":0.36,"c1W":6.34,"c1M":11.55},"DIS":{"symbol":"DIS","name":"Walt Disney Company (The)","price":103.24,"change":-2.18,"changePercent":-2.0679,"volume":2638465,"avgVolume":10083870,"score":-1.5,"signal":"HOLD","rsi":49.1,"macd":1.031,"macdSig":1.1433,"macdHist":-0.1123,"macdUp":false,"macdDn":true,"sma20":104.23,"sma50":101.09,"ema50":103.22,"ema200":107.05,"goldenCross":false,"deathCross":false,"adx":18.0,"diP":27.7,"diN":25.7,"volVs65":0.26,"c1W":-4.43,"c1M":-0.64},"VZ":{"symbol":"VZ","name":"Verizon Communications Inc.","price":47.21,"change":0.1476,"changePercent":0.3136,"volume":6199051,"avgVolume":25771446,"score":3.0,"signal":"BUY","rsi":48.9,"macd":-0.0488,"macdSig":-0.0941,"macdHist":0.0453,"macdUp":false,"macdDn":false,"sma20":47.13,"sma50":48.03,"ema50":47.15,"ema200":44.08,"goldenCross":false,"deathCross":false,"adx":12.8,"diP":19.5,"diN":18.1,"volVs65":0.23,"c1W":-0.03,"c1M":0.91},"T":{"symbol":"T","name":"AT&T Inc.","price":24.74,"change":0.0901,"changePercent":0.3655,"volume":9907046,"avgVolume":39217645,"score":1.5,"signal":"HOLD","rsi":35.7,"macd":-0.537,"macdSig":-0.4711,"macdHist":-0.0659,"macdUp":false,"macdDn":false,"sma20":25.63,"sma50":26.73,"ema50":26.18,"ema200":26.17,"goldenCross":false,"deathCross":false,"adx":35.1,"diP":10.8,"diN":30.3,"volVs65":0.25,"c1W":-1.67,"c1M":-6.29},"NEE":{"symbol":"NEE","name":"NextEra Energy, Inc.","price":93.85,"change":-1.835,"changePercent":-1.9179,"volume":2787607,"avgVolume":9242735,"score":3.0,"signal":"BUY","rsi":49.0,"macd":0.4827,"macdSig":0.6632,"macdHist":-0.1804,"macdUp":false,"macdDn":false,"sma20":94.59,"sma50":93.1,"ema50":92.99,"ema200":85.5,"goldenCross":false,"deathCross":false,"adx":12.5,"diP":19.0,"diN":18.9,"volVs65":0.3,"c1W":0.8,"c1M":2.19},"DUK":{"symbol":"DUK","name":"Duke Energy Corporation (Holdin","price":121.62,"change":-2.69,"changePercent":-2.1639,"volume":1292175,"avgVolume":3962553,"score":2.0,"signal":"HOLD","rsi":32.5,"macd":-1.4599,"macdSig":-1.0583,"macdHist":-0.4016,"macdUp":false,"macdDn":false,"sma20":126.15,"sma50":128.75,"ema50":126.95,"ema200":122.96,"goldenCross":false,"deathCross":false,"adx":24.6,"diP":11.5,"diN":33.7,"volVs65":0.32,"c1W":-2.05,"c1M":-5.45},"AVB":{"symbol":"AVB","name":"AvalonBay Communities, Inc.","price":181.95,"change":-1.59,"changePercent":-0.8663,"volume":195112,"avgVolume":1008332,"score":-1.0,"signal":"HOLD","rsi":55.2,"macd":3.6557,"macdSig":3.9809,"macdHist":-0.3252,"macdUp":false,"macdDn":true,"sma20":181.22,"sma50":172.66,"ema50":176.61,"ema200":178.92,"goldenCross":false,"deathCross":false,"adx":36.3,"diP":23.1,"diN":15.6,"volVs65":0.19,"c1W":-1.16,"c1M":7.26}}}